ganskit/__init__.py
ganskit/__pycache__/__init__.cpython-36.pyc
ganskit/__pycache__/__init__.cpython-39.pyc
ganskit/cgan/__init__.py
ganskit/cgan/fid.py
ganskit/cgan/step1_create_h5_dataset.py
ganskit/cgan/step2_cGAN_train.py
ganskit/cgan/step3_cGAN_generate.py
ganskit/cgan/step4_cGAN_evaluate.py
ganskit/cgan/step5_cGAN_evaluate_summary.py
ganskit/cgan/step6_cGAN_inception_score.py
ganskit/cgan/__pycache__/__init__.cpython-36.pyc
ganskit/cgan/__pycache__/__init__.cpython-39.pyc
ganskit/cgan/__pycache__/fid.cpython-36.pyc
ganskit/cgan/__pycache__/fid.cpython-39.pyc
ganskit/cgan/__pycache__/step1_create_h5_dataset.cpython-36.pyc
ganskit/cgan/__pycache__/step1_create_h5_dataset.cpython-39.pyc
ganskit/cgan/__pycache__/step2_cGAN_train.cpython-36.pyc
ganskit/cgan/__pycache__/step2_cGAN_train.cpython-39.pyc
ganskit/cgan/__pycache__/step3_cGAN_generate.cpython-36.pyc
ganskit/cgan/__pycache__/step3_cGAN_generate.cpython-39.pyc
ganskit/cgan/__pycache__/step4_cGAN_evaluate.cpython-36.pyc
ganskit/cgan/__pycache__/step4_cGAN_evaluate.cpython-39.pyc
ganskit/cgan/__pycache__/step6_cGAN_inception_score.cpython-36.pyc
ganskit/cgan/__pycache__/step6_cGAN_inception_score.cpython-39.pyc
gans_kit-0.0.1a2.dist-info/LICENSE
gans_kit-0.0.1a2.dist-info/METADATA
gans_kit-0.0.1a2.dist-info/WHEEL
gans_kit-0.0.1a2.dist-info/top_level.txt
gans_kit-0.0.1a2.dist-info/RECORD
