Metadata-Version: 2.1
Name: gans-kit
Version: 0.0.1a2
Summary: A toolkit to train and test various GAN models
Home-page: https://github.com/dhchenx/gans-kit
Author: Donghua Chen
Author-email: douglaschan@126.com
Project-URL: Bug Reports, https://github.com/dhchenx/gans-kit/issues
Project-URL: Source, https://github.com/dhchenx/gans-kit
Keywords: generative adversarial network,GAN,gans toolkit,image generation
Classifier: Development Status :: 5 - Production/Stable
Classifier: Intended Audience :: Developers
Classifier: Topic :: Software Development :: Build Tools
Classifier: License :: OSI Approved :: MIT License
Classifier: Programming Language :: Python :: 3
Classifier: Programming Language :: Python :: 3.6
Classifier: Programming Language :: Python :: 3.7
Classifier: Programming Language :: Python :: 3.8
Classifier: Programming Language :: Python :: 3.9
Classifier: Programming Language :: Python :: 3 :: Only
Requires-Python: >=3.6, <4
License-File: LICENSE
Requires-Dist: scipy
Requires-Dist: tensorflow
Requires-Dist: imageio
Requires-Dist: h5py
Requires-Dist: matplotlib
Requires-Dist: opencv-python
Requires-Dist: numpy
Requires-Dist: keras
Requires-Dist: torch
Requires-Dist: torchvision
Provides-Extra: dev
Requires-Dist: check-manifest ; extra == 'dev'
Provides-Extra: test
Requires-Dist: coverage ; extra == 'test'
